{
  "title": "La SNCF lance son site e-commerce",
  "smallDate": "",
  "bigDate": "1999-12-31T23:00:00.000Z",
  "description": "Le premier à lancer un site e-commerce de vente de billets de train en France en 2000.",
  "body": "Le premier à lancer un site e-commerce de vente de billets de train en France en 2000.\n\nLa SNCF est un pionnier de l'innovation.\n\nLancé en 2000, Voyages-SNCF.com est un site français e-commerce spécialisé dans la vente de billets de train et la réservation d'hébergements. Plus de 83 millions de billets ont été achetés via Voyages-SNCF.com en 2015, dont environ 12 millions par des voyageurs internationaux. Filiale du groupe SNCF, le site a également développé son offre dans le domaine de l'e-tourisme européen. Le coeur de métier de Voyages-SNCF.com reste la vente de billets de train (TGV, Thalys, Eurostar, lignes TER...), mais des billets d'avions et de bus sont également proposés, sans oublier la location de voitures, la réservation de chambres d'hôtels et l'organisation de séjours.",
  "thumbnail": "/img/voyages-sncf.png"
}